ternary_diagram/__init__.py
ternary_diagram/_test.py
ternary_diagram/ternary_diagram.py
ternary_diagram/utils.py
ternary_diagram-3.1.0.dist-info/LICENSE
ternary_diagram-3.1.0.dist-info/METADATA
ternary_diagram-3.1.0.dist-info/WHEEL
ternary_diagram-3.1.0.dist-info/top_level.txt
ternary_diagram-3.1.0.dist-info/RECORD
