Metadata-Version: 2.1
Name: ternary-diagram
Version: 3.1.0
Summary: This package makes it easier for you to draw beautiful ternary diagram without pymatgen.
Author: yu9824
Author-email: yu.9824.job@gmail.com
Maintainer: yu9824
Maintainer-email: yu.9824.job@gmail.com
License: MIT
Project-URL: Documentation, https://yu9824.github.io/ternary_diagram/
Project-URL: Source, http://github.com/yu9824/ternary_diagram/
Project-URL: Tracker, http://github.com/yu9824/ternary_diagram//issues
Project-URL: PyPI, https://pypi.org/project/ternary-diagram/
Keywords: ternarydiagram phasediagram chemistry
Classifier: License :: OSI Approved :: MIT License
Classifier: Programming Language :: Python :: 3
Classifier: Programming Language :: Python :: 3.7
Classifier: Programming Language :: Python :: 3.8
Classifier: Programming Language :: Python :: 3.9
Classifier: Programming Language :: Python :: 3.10
Classifier: Programming Language :: Python :: 3.11
Classifier: Topic :: Scientific/Engineering :: Chemistry
Classifier: Topic :: Scientific/Engineering :: Visualization
License-File: LICENSE
Requires-Dist: numpy >=1.20
Requires-Dist: matplotlib
